toco/__init__.py
toco/object.py
toco-0.0.9.dist-info/LICENSE
toco-0.0.9.dist-info/METADATA
toco-0.0.9.dist-info/WHEEL
toco-0.0.9.dist-info/top_level.txt
toco-0.0.9.dist-info/RECORD
