Metadata-Version: 2.1
Name: toco
Version: 0.0.9
Summary: Basic tools for interacting with DynamoDB.
Home-page: https://github.com/stevenorum/toco
Author: Steve Norum
Author-email: sn@drunkenrobotlabs.org
License: UNKNOWN
Download-URL: https://github.com/stevenorum/toco/archive/0.0.9.tar.gz
Keywords: python,aws,dynamodb
Platform: UNKNOWN
Requires-Dist: boto3
